simple_slotted_dataclasses.py
simple_slotted_dataclasses-0.0.1.dist-info/LICENSE.md
simple_slotted_dataclasses-0.0.1.dist-info/METADATA
simple_slotted_dataclasses-0.0.1.dist-info/WHEEL
simple_slotted_dataclasses-0.0.1.dist-info/top_level.txt
simple_slotted_dataclasses-0.0.1.dist-info/RECORD
