Metadata-Version: 2.1
Name: simple-slotted-dataclasses
Version: 0.0.1
Summary: Simple library on top of dataclasses to create slotted dataclasses in python <3.10.
Author-email: Egor Stakhovsky <y.stakhovsky@gmail.com>
Project-URL: Homepage, https://github.com/stakhovsky/simple-slotted-dataclasses
Project-URL: Bug Tracker, https://github.com/stakhovsky/simple-slotted-dataclasses/issues
Classifier: Programming Language :: Python :: 3
Classifier: License :: Other/Proprietary License
Classifier: Operating System :: OS Independent
Requires-Python: <3.10,>=3.7
License-File: LICENSE.md
